MANIFEST.in
README.md
README.rst
requirements.txt
setup.py
image_search/__init__.py
image_search/main_search.py
image_search/search_files/__init__.py
image_search/search_files/fb_search.py
image_search/search_files/github_search.py
image_search/search_files/instagram_search.py
image_search/search_files/linkedin_search.py
image_search/search_files/quora_search.py
imagyy.egg-info/PKG-INFO
imagyy.egg-info/SOURCES.txt
imagyy.egg-info/dependency_links.txt
imagyy.egg-info/entry_points.txt
imagyy.egg-info/pbr.json
imagyy.egg-info/requires.txt
imagyy.egg-info/top_level.txt