Metadata-Version: 1.1
Name: imagyy
Version: 1.0.3
Summary: Fetches public photos of different social networking platforms
Home-page: https://github.com/tusharmakkar08/Imagyy/
Author: Tushar Makkar
Author-email: tusharmakkar08@gmail.com
License: MIT
Platform: any
Classifier: Development Status :: 5 - Production/Stable
Classifier: Intended Audience :: Developers
Classifier: Operating System :: OS Independent
Classifier: Programming Language :: Python :: 2
Classifier: Programming Language :: Python :: 2.7
Classifier: Programming Language :: Python :: 3
Classifier: Programming Language :: Python :: 3.1
Classifier: Programming Language :: Python :: 3.2
Classifier: Programming Language :: Python :: 3.3
Classifier: Programming Language :: Python :: 3.4
